Metadata-Version: 2.1
Name: odoo12-addon-stock-demand-estimate-matrix
Version: 12.0.2.0.0
Summary: Allows to create demand estimates.
Home-page: https://github.com/OCA/stock-logistics-warehouse
Author: ForgeFlow, Odoo Community Association (OCA)
Author-email: support@odoo-community.org
License: AGPL-3
Platform: UNKNOWN
Classifier: Programming Language :: Python
Classifier: Framework :: Odoo
Classifier: License :: OSI Approved :: GNU Affero General Public License v3
Requires-Python: >=3.5
Requires-Dist: odoo12-addon-date-range
Requires-Dist: odoo12-addon-stock-demand-estimate
Requires-Dist: odoo12-addon-web-widget-x2many-2d-matrix
Requires-Dist: odoo (<12.1dev,>=12.0a)
